<?xml version="1.0" encoding="utf-8" standalone="yes"?>
<post>
  <author>zarif</author>
  <title>ستایش</title>
  <description />
  <content>&lt;p style="text-align: right;"&gt;&lt;br /&gt;&lt;strong&gt;&lt;span style="font-size: small;"&gt;پس بر محمد و آلش درود فرست و به رحمتت - الها - در آسايش را به رويم باز كن و&lt;/span&gt;&lt;/strong&gt;&lt;/p&gt;
&lt;p style="text-align: right;"&gt;&lt;strong&gt;&lt;span style="font-size: small;"&gt;به قدرتت سلطنت غم را در زندگيم درهم بشكن و به من در موردى كه از آن شكوه&lt;/span&gt;&lt;/strong&gt;&lt;/p&gt;
&lt;p style="text-align: right;"&gt;&lt;strong&gt;&lt;span style="font-size: small;"&gt;دارم با ديده عنايت و احسانت بنگر و به من در مورد در خواستم شيرينى اجابت&lt;/span&gt;&lt;/strong&gt;&lt;/p&gt;
&lt;p style="text-align: right;"&gt;&lt;strong&gt;&lt;span style="font-size: small;"&gt;بچشان و از سوى خودت رحمت و گشايش دلخواه نصيبم فرما و برايم نجات و خلاصى&lt;/span&gt;&lt;/strong&gt;&lt;/p&gt;
&lt;p style="text-align: right;"&gt;&lt;strong&gt;&lt;span style="font-size: small;"&gt;سريع از گرفتاري ها مقرر كن&amp;rlm; و مرا به خاطر غم و اندوه از رعايت واجبات و به كار&lt;/span&gt;&lt;/strong&gt;&lt;/p&gt;
&lt;p style="text-align: right;"&gt;&lt;strong&gt;&lt;span style="font-size: small;"&gt;بستن مستحبات خود باز مدار&lt;/span&gt;&lt;/strong&gt;&lt;/p&gt;
&lt;p style="text-align: right;"&gt;&lt;strong&gt;&lt;/strong&gt;&lt;/p&gt;
&lt;p style="text-align: center;"&gt;&lt;img src="/image.axd?picture=2013%2f2%2f13169353735.jpg" alt="" width="358" height="226" /&gt;&lt;/p&gt;</content>
  <ispublished>True</ispublished>
  <iscommentsenabled>True</iscommentsenabled>
  <pubDate>2013-02-19 07:39:00</pubDate>
  <lastModified>2013-02-19 07:43:19</lastModified>
  <raters>6</raters>
  <rating>4.5</rating>
  <slug>d8b3d8aad8a7db8cd8b4</slug>
  <tags />
  <comments />
  <categories>
    <category>5bd9fe46-0d83-454b-b81d-61724a8938e3</category>
    <category>006109d7-9b5f-489c-832c-8d34c3d71b28</category>
  </categories>
  <notifications />
</post>