<?xml version="1.0" encoding="utf-8" standalone="yes"?>
<post>
  <author>ahoseini</author>
  <title>درنرم افزار ADSL نحوه ثبت دایری</title>
  <description />
  <content>&lt;p&gt;&amp;nbsp;&lt;/p&gt;
&lt;h6 style="TEXT-ALIGN: right"&gt;&amp;nbsp;&amp;nbsp;&lt;/h6&gt;
&lt;p class="MsoNormal" style="text-justify: kashida; text-align: right; text-kashida: 0%; margin: 0cm 0cm 0pt; mso-outline-level: 1;" dir="rtl"&gt;&lt;span style="font-size: small;"&gt;&lt;span style="font-family: &amp;quot;B Titr&amp;quot;; color: black; mso-ascii-font-family: Arial; mso-hansi-font-family: Arial; mso-font-kerning: 18.0pt;"&gt;&lt;span lang="AR-SA"&gt;1-انجام هرعملیات رانژه کشی درکافوی نوری معادل یک مورد دایری Adsl می باشد(با تحویل خط به مشترک ویا بدون تحویل)&lt;/span&gt;&lt;/span&gt;&lt;/span&gt;&lt;/p&gt;
&lt;p class="MsoNormal" style="text-justify: kashida; text-align: right; text-kashida: 0%; margin: 0cm 0cm 0pt; mso-outline-level: 1;" dir="rtl"&gt;&lt;span style="font-family: &amp;quot;B Titr&amp;quot;; color: black; mso-ascii-font-family: Arial; mso-hansi-font-family: Arial; mso-font-kerning: 18.0pt;" lang="AR-SA"&gt;&lt;span style="font-size: small;"&gt;2-انجام هرعملیات برگردان ازروی ریموت &lt;span style="mso-spacerun: yes;"&gt;&amp;nbsp;&lt;/span&gt;&lt;/span&gt;&lt;/span&gt;&lt;span style="font-size: small;"&gt;&lt;span style="font-family: Arial; color: black; mso-font-kerning: 18.0pt; mso-bidi-font-family: 'B Titr';" dir="ltr"&gt;Pcmx&lt;/span&gt;&lt;span style="font-family: &amp;quot;B Titr&amp;quot;; color: black; mso-ascii-font-family: Arial; mso-hansi-font-family: Arial; mso-font-kerning: 18.0pt;" lang="AR-SA"&gt;(&lt;span style="background: yellow; mso-highlight: yellow;"&gt;خارج کردن خط ازروی ریموت&lt;/span&gt; ) و.... به منظور ایجاد امکانات بدون &lt;span style="background: yellow; mso-highlight: yellow;"&gt;عملیات کابلکشی&lt;/span&gt; معادل یک مورد دایری &lt;/span&gt;&lt;span style="font-family: Arial; color: black; mso-font-kerning: 18.0pt; mso-bidi-font-family: 'B Titr';" dir="ltr"&gt;adsl &lt;/span&gt;&lt;span style="font-family: &amp;quot;B Titr&amp;quot;; color: black; mso-ascii-font-family: Arial; mso-hansi-font-family: Arial; mso-font-kerning: 18.0pt;"&gt;&lt;span style="mso-spacerun: yes;"&gt;&amp;nbsp;&lt;/span&gt;&lt;span lang="AR-SA"&gt;می باشد(&lt;em&gt;&lt;span style="text-decoration: underline;"&gt;درقراردادهای که برای این برگردان تعریفی وجود ندارد&lt;/span&gt;&lt;/em&gt;)(با تحویل خط به مشترک ویا بدون تحویل)&lt;/span&gt;&lt;/span&gt;&lt;/span&gt;&lt;/p&gt;
&lt;p class="MsoNormal" style="text-justify: kashida; text-align: right; text-kashida: 0%; margin: 0cm 0cm 0pt; mso-outline-level: 1;" dir="rtl"&gt;&lt;span style="font-size: small;"&gt;&lt;span style="font-family: &amp;quot;B Titr&amp;quot;; color: black; mso-ascii-font-family: Arial; mso-hansi-font-family: Arial; mso-font-kerning: 18.0pt;" lang="AR-SA"&gt;3-تحویل هردایری &lt;/span&gt;&lt;span style="font-family: Arial; color: black; mso-font-kerning: 18.0pt; mso-bidi-font-family: 'B Titr';" dir="ltr"&gt;adsl&lt;/span&gt;&lt;span style="font-family: &amp;quot;B Titr&amp;quot;; color: black; mso-ascii-font-family: Arial; mso-hansi-font-family: Arial; mso-font-kerning: 18.0pt;"&gt; &lt;span lang="AR-SA"&gt;به مشترک بدون عملیات فوق معادل یک مورد دایری &lt;/span&gt;&lt;/span&gt;&lt;span style="font-family: Arial; color: black; mso-font-kerning: 18.0pt; mso-bidi-font-family: 'B Titr';" dir="ltr"&gt;adsl &lt;/span&gt;&lt;span style="font-family: &amp;quot;B Titr&amp;quot;; color: black; mso-ascii-font-family: Arial; mso-hansi-font-family: Arial; mso-font-kerning: 18.0pt;"&gt;&lt;span style="mso-spacerun: yes;"&gt;&amp;nbsp;&lt;/span&gt;&lt;span lang="AR-SA"&gt;می باشد(مراکزی که پیمانکار جهت تحویل &lt;/span&gt;&lt;/span&gt;&lt;span style="font-family: Arial; color: black; mso-font-kerning: 18.0pt; mso-bidi-font-family: 'B Titr';" dir="ltr"&gt;adsl&lt;/span&gt;&lt;span style="font-family: &amp;quot;B Titr&amp;quot;; color: black; mso-ascii-font-family: Arial; mso-hansi-font-family: Arial; mso-font-kerning: 18.0pt;"&gt; &lt;span lang="AR-SA"&gt;ندارند وخود مامورین شبکه این کاررا انجام می دهند)&lt;/span&gt;&lt;/span&gt;&lt;/span&gt;&lt;/p&gt;
&lt;p class="MsoNormal" style="text-justify: kashida; text-align: justify; text-kashida: 0%; margin: 0cm 0cm 0pt;" dir="rtl"&gt;&lt;span style="mso-bidi-font-family: 'B Titr';" dir="ltr"&gt;&lt;span style="font-family: Times New Roman; font-size: small;"&gt;&amp;nbsp;&lt;/span&gt;&lt;/span&gt;&lt;/p&gt;
&lt;p class="MsoNormal" style="text-align: right; margin: 0cm 0cm 0pt; mso-outline-level: 1;" dir="rtl"&gt;&amp;nbsp;&lt;/p&gt;</content>
  <ispublished>True</ispublished>
  <iscommentsenabled>True</iscommentsenabled>
  <pubDate>2015-06-22 11:40:00</pubDate>
  <lastModified>2015-10-17 08:04:54</lastModified>
  <raters>2</raters>
  <rating>5</rating>
  <slug>d986d8add988d987-d8abd8a8d8aa-d8afd8a7db8cd8b1db8c-ADSL-d8afd8b1d986d8b1d985-d8a7d981d8b2d8a7d8b1</slug>
  <tags />
  <comments />
  <categories />
  <notifications />
</post>