<?xml version="1.0" encoding="utf-8" standalone="yes"?>
<post>
  <author>hheydari</author>
  <title>نهم دی روز بصیرت و میثاق با ولایت</title>
  <description />
  <content>&lt;p style="text-align: right;"&gt;&amp;nbsp;نهم دی&amp;nbsp;یاد آور روزی بزرگ برای ملت قهرمان ایران است روزی که فتنه ها و بدی ها در اقیانوس مواج ملت ایران شسته شده و برای ابد به زباله دان تاریخ پیوستند نهم دی&amp;nbsp;سال 1388 را همه بیاد داریم&amp;nbsp;روزی که بعد از 8 ماه فتنه گری و فتنه انگیزی گروهی معاند با نظام و ولایت مردم ولایت مدار&amp;nbsp;ایران اسلامی نگذاشتند نامشان چون کوفیان به بدی یاد شود و نشان دادند که ایرانی ها اهل کوفه نیستند که مولا و مقتدایشان تنها بماند. فتنته گران در 8 ماه فتنه انگیزی شان هیچ خط قرمزی&amp;nbsp;برای&amp;nbsp;اعمالشان نگذاشته بودند .&amp;nbsp;از&amp;nbsp;شعار استقلال آزادی جمهوری اسلامی اسلام را حذف نمودند به&amp;nbsp;امام خمینی (ره)&amp;nbsp;اهانت نمودند با&amp;nbsp;پاره کردن عکس آن&amp;nbsp;پیر سفر کرده به ولایت فقیه اهانت نمودند و در آخر&amp;nbsp;حتی حرمت&amp;nbsp;تاسوعا و عاشورا و اما حسین(ع) را نگه نداشتند و&amp;nbsp;به تکایا و حسینیه ها و دسته جات عزاداری حمله کردند و بعضی از تکایا را&amp;nbsp;به آتش کشیدند و دیگر کاسه صبر ملت مسلمان و همیشه در صحنه&amp;nbsp;لبریز شد و این شد که در 9 دی 1388 مردم با حضور میلیونی شان&amp;nbsp;باز هم تاریخ&amp;nbsp;ساز شدند&amp;nbsp;و &amp;nbsp;به کسانی که دل خوش به شکست نظام اسلامی بودند فهماندند که این ملت تا آخرین نفس در کنار ولایت مطلقه&amp;nbsp;فقیه خواهد ایستاد و به کوری چشم دشمنان این نظام&amp;nbsp;شعار مردم ایران این خواهد بود&lt;/p&gt;
&lt;p style="text-align: center;"&gt;&lt;span style="font-family: arial black,avant garde;"&gt;&lt;strong&gt;تا زنده ایم رزمنده ایم - خونی که در رگ ماست هدیه به رهبر ماست&lt;/strong&gt;&amp;nbsp;&amp;nbsp;&lt;/span&gt;&amp;nbsp;&amp;nbsp;&amp;nbsp;&amp;nbsp;&amp;nbsp;&lt;/p&gt;
&lt;p&gt;&lt;img src="/image.axd?picture=2012%2f12%2f9010091%5b1%5d.jpg" alt="" width="597" height="891" /&gt;&lt;/p&gt;</content>
  <ispublished>True</ispublished>
  <iscommentsenabled>True</iscommentsenabled>
  <pubDate>2012-12-30 12:58:00</pubDate>
  <lastModified>2012-12-30 13:47:37</lastModified>
  <raters>4</raters>
  <rating>4.5</rating>
  <slug>d986d987d985-d8afdb8c-d8b1d988d8b2-d8a8d8b5db8cd8b1d8aa-d988-d985db8cd8abd8a7d982-d8a8d8a7-d988d984d8a7db8cd8aa</slug>
  <tags />
  <comments />
  <categories>
    <category>5bd9fe46-0d83-454b-b81d-61724a8938e3</category>
  </categories>
  <notifications />
</post>